driftmlp/__init__.py
driftmlp/helpers.py
driftmlp/data/transition_both.GraphML
driftmlp/drifter_indexing/discrete_system.py
driftmlp/drifter_indexing/driftiter/__init__.py
driftmlp/drifter_indexing/makehdf5/__init__.py
driftmlp/drifter_indexing/story/__init__.py
driftmlp/form_network/__init__.py
driftmlp/plotting/__init.__.py
driftmlp/plotting/general.py
driftmlp/plotting/h3_cartopy.py
driftmlp/plotting/h3_plotly.py
driftmlp/plotting/make_gpd.py
driftmlp/plotting/shape_helpers.py
driftmlp/rotations/__init__.py
driftmlp/shortest_path/__init__.py
driftmlp-1.2.dist-info/LICENSE.txt
driftmlp-1.2.dist-info/METADATA
driftmlp-1.2.dist-info/WHEEL
driftmlp-1.2.dist-info/top_level.txt
driftmlp-1.2.dist-info/RECORD
