Metadata-Version: 2.1
Name: driftmlp
Version: 1.2
Summary: A set of tools for data extraction from the GDP database and estimating travel times
Home-page: https://github.com/MikeOMa/DriftMLP
Author: Mike O'Malley
Author-email: m.omalley2@lancaster.ac.uk
License: UNKNOWN
Platform: UNKNOWN
Classifier: Programming Language :: Python :: 3.7
Classifier: License :: OSI Approved :: MIT License
Classifier: Operating System :: OS Independent
Requires-Dist: numpy (<=1.20,>=1.17.2)
Requires-Dist: cartopy (>=0.17)
Requires-Dist: h3 (>=3.6.4)
Requires-Dist: scipy (>=1.3.1)
Requires-Dist: python-igraph (>0.8)
Requires-Dist: h5py
Requires-Dist: folium
Requires-Dist: geopandas
Requires-Dist: pyproj (>=2.2.0)
Requires-Dist: matplotlib
Requires-Dist: numba
